open_review_abstract_bot/__init__.py
open_review_abstract_bot/console.py
open_review_abstract_bot/main.py
open_review_abstract_bot-0.2.2.dist-info/entry_points.txt
open_review_abstract_bot-0.2.2.dist-info/LICENSE
open_review_abstract_bot-0.2.2.dist-info/WHEEL
open_review_abstract_bot-0.2.2.dist-info/METADATA
open_review_abstract_bot-0.2.2.dist-info/RECORD
